gha_ci_detector/Job.py
gha_ci_detector/Runner.py
gha_ci_detector/Step.py
gha_ci_detector/Workflow.py
gha_ci_detector/__init__.py
gha_ci_detector/__main__.py
gha_ci_detector/cli.py
gha_ci_detector/smell_detector.py
gha_ci_detector/util.py
gha_ci_detector-0.0.3.dist-info/METADATA
gha_ci_detector-0.0.3.dist-info/WHEEL
gha_ci_detector-0.0.3.dist-info/entry_points.txt
gha_ci_detector-0.0.3.dist-info/RECORD
